paquete_ejemplo5/__init__.py
paquete_ejemplo5/ejemplo5.py
ejemplopackupp5-0.0.1.dist-info/LICENSE
ejemplopackupp5-0.0.1.dist-info/METADATA
ejemplopackupp5-0.0.1.dist-info/WHEEL
ejemplopackupp5-0.0.1.dist-info/top_level.txt
ejemplopackupp5-0.0.1.dist-info/RECORD
