Metadata-Version: 2.1
Name: ejemplopackupp5
Version: 0.0.1
Summary: Prueba
Home-page: https://github.com/francomrf/Costeo_Python.git
Author: Franco F
Author-email: francomrf@gmail.com
License: UNKNOWN
Project-URL: Bug Tracker, https://github.com/francomrf/Costeo_Python.git
Platform: UNKNOWN
Classifier: Programming Language :: Python :: 3
Classifier: License :: OSI Approved :: MIT License
Classifier: Operating System :: OS Independent
Requires-Python: >=3.6
License-File: LICENSE
